text_selector/__init__.py
text_selector/_version.py
text_selector/widget.py
text_selector/static/extension.js
text_selector/static/index.js
text_selector/static/index.js.map
text_selector-2.3.0.data/data/etc/jupyter/nbconfig/notebook.d/text_selector.json
text_selector-2.3.0.data/data/share/jupyter/nbextensions/text_selector/extension.js
text_selector-2.3.0.data/data/share/jupyter/nbextensions/text_selector/index.js
text_selector-2.3.0.data/data/share/jupyter/nbextensions/text_selector/index.js.map
text_selector-2.3.0.dist-info/METADATA
text_selector-2.3.0.dist-info/WHEEL
text_selector-2.3.0.dist-info/top_level.txt
text_selector-2.3.0.dist-info/RECORD
